mrmn0/__init__.py
mrmn0/mrmn0.py
mrmn0-0.1.0.dist-info/licenses/LICENSE
mrmn0-0.1.0.dist-info/METADATA
mrmn0-0.1.0.dist-info/WHEEL
mrmn0-0.1.0.dist-info/top_level.txt
mrmn0-0.1.0.dist-info/RECORD
